ssh_mock/__init__.py
ssh_mock/cli.py
ssh_mock/command.py
ssh_mock/connection_handler.py
ssh_mock/server.py
ssh_mock/server_key
ssh_mock/utils.py
ssh_mock-0.3.1.dist-info/METADATA
ssh_mock-0.3.1.dist-info/WHEEL
ssh_mock-0.3.1.dist-info/entry_points.txt
ssh_mock-0.3.1.dist-info/RECORD
