Metadata-Version: 2.1
Name: ssh-mock
Version: 0.3.1
Summary: Mocks an SSH Server
Home-page: https://github.com/DanielHabenicht/mock-ssh.git
License: MIT
Keywords: SSH,Server,Mocking,Mock,Testing
Author: DanielHabenicht
Author-email: daniel-habenicht@outlook.de
Requires-Python: >=3.8.1,<4.0.0
Classifier: License :: OSI Approved :: MIT License
Classifier: Programming Language :: Python :: 3
Classifier: Programming Language :: Python :: 3.9
Classifier: Programming Language :: Python :: 3.10
Classifier: Programming Language :: Python :: 3.11
Requires-Dist: jinja2 (>=3.1.2,<4.0.0)
Requires-Dist: paramiko (==3.3.1)
Requires-Dist: pyyaml (>=6.0.1,<7.0.0)
Project-URL: Repository, https://github.com/DanielHabenicht/mock-ssh.git
